vserialport/__init__.py
vserialport/ConcreteSerial.py
vserialport/ListConcreteSerialPorts.py
vserialport/objectTransaction.py
vserialport/PortManager.py
vserialport/SerialPort_.py
vserialport-0.1.1.dist-info/WHEEL
vserialport-0.1.1.dist-info/METADATA
vserialport-0.1.1.dist-info/RECORD
